learners/__init__.py
learners/__main__.py
learners/assets.py
learners/database.py
learners/jwt_manager.py
learners/logger.py
learners/conf/__init__.py
learners/conf/admin.py
learners/conf/config.py
learners/conf/config_schema.py
learners/conf/db_models.py
learners/conf/jwt_manager.py
learners/functions/__init__.py
learners/functions/authentication.py
learners/functions/database.py
learners/functions/execution.py
learners/functions/helpers.py
learners/functions/results.py
learners/routes/__init__.py
learners/routes/admin.py
learners/routes/authentication.py
learners/routes/callback.py
learners/routes/comment.py
learners/routes/execution.py
learners/routes/home.py
learners/routes/interface.py
learners/routes/statics.py
learners/static/css/_admin.scss
learners/static/css/_base.scss
learners/static/css/_chat.scss
learners/static/css/_colors_dark.scss
learners/static/css/_colors_light.scss
learners/static/css/_form.scss
learners/static/css/_screensharing.scss
learners/static/css/_sidebar.scss
learners/static/css/_variables.scss
learners/static/css/bootstrap-5.1.3.min.css
learners/static/css/theme_dark.scss
learners/static/css/theme_light.scss
learners/static/favicon/apple-touch-icon.png
learners/static/favicon/favicon-16x16.png
learners/static/favicon/favicon-32x32.png
learners/static/favicon/safari-pinned-tab.svg
learners/static/fonts/rubik-v21-latin-300.eot
learners/static/fonts/rubik-v21-latin-300.svg
learners/static/fonts/rubik-v21-latin-300.ttf
learners/static/fonts/rubik-v21-latin-300.woff
learners/static/fonts/rubik-v21-latin-300.woff2
learners/static/fonts/rubik-v21-latin-600.eot
learners/static/fonts/rubik-v21-latin-600.svg
learners/static/fonts/rubik-v21-latin-600.ttf
learners/static/fonts/rubik-v21-latin-600.woff
learners/static/fonts/rubik-v21-latin-600.woff2
learners/static/fonts/rubik-v21-latin-700.eot
learners/static/fonts/rubik-v21-latin-700.svg
learners/static/fonts/rubik-v21-latin-700.ttf
learners/static/fonts/rubik-v21-latin-700.woff
ait_learners-0.6.4.dist-info/METADATA
ait_learners-0.6.4.dist-info/WHEEL
ait_learners-0.6.4.dist-info/top_level.txt
ait_learners-0.6.4.dist-info/RECORD
